extracttoc/__init__.py
extracttoc/extracttoc.py
extracttoc-0.4.0.dist-info/LICENSE
extracttoc-0.4.0.dist-info/METADATA
extracttoc-0.4.0.dist-info/WHEEL
extracttoc-0.4.0.dist-info/entry_points.txt
extracttoc-0.4.0.dist-info/top_level.txt
extracttoc-0.4.0.dist-info/RECORD
