Metadata-Version: 2.1
Name: extracttoc
Version: 0.4.0
Summary: A CLI package to extract and create a table of contents from markdown files.
Home-page: https://github.com/CribberSix/markdown-toc-extract
Author: CribberSix
Author-email: cribbersix@gmail.com
License: UNKNOWN
Platform: UNKNOWN
Classifier: Development Status :: 5 - Production/Stable
Classifier: Programming Language :: Python :: 3
Classifier: Topic :: Software Development :: Libraries
Classifier: Topic :: Software Development :: Libraries :: Python Modules
Classifier: Intended Audience :: Developers
Classifier: Natural Language :: English
Classifier: Topic :: Software Development
Requires-Python: >=3.6
Requires-Dist: regex
Requires-Dist: clipboard
